py_populate_dcim/__init__.py
py_populate_dcim/api/models.py
py_populate_dcim/api/serializers.py
py_populate_dcim/api/urls.py
py_populate_dcim/api/views.py
py_populate_dcim/app-config-schema.json
py_populate_dcim/migrations/0001_initial.py
py_populate_dcim/migrations/__init__.py
py_populate_dcim/navigation.py
py_populate_dcim/templates/py_populate_dcim/appview.html
py_populate_dcim/tests/__init__.py
py_populate_dcim/tests/test_api.py
py_populate_dcim/tests/test_basic.py
py_populate_dcim/urls.py
py_populate_dcim/views.py
py_populate_dcim-0.1.2.4.dist-info/LICENSE
py_populate_dcim-0.1.2.4.dist-info/METADATA
py_populate_dcim-0.1.2.4.dist-info/WHEEL
py_populate_dcim-0.1.2.4.dist-info/RECORD
