Metadata-Version: 2.1
Name: py-populate-dcim
Version: 0.1.2.4
Summary: Py Populate Dcim
Home-page: https://git.autonaut.dev/autonaut/nautobot-app-py-populate-dcim
License: Apache-2.0
Keywords: nautobot,nautobot-app,nautobot-plugin
Author: Etherflow
Author-email: alan@etherflow.io
Requires-Python: >=3.9,<3.13
Classifier: Development Status :: 5 - Production/Stable
Classifier: Intended Audience :: Developers
Classifier: License :: OSI Approved :: Apache Software License
Classifier: Programming Language :: Python :: 3
Classifier: Programming Language :: Python :: 3.9
Classifier: Programming Language :: Python :: 3.10
Classifier: Programming Language :: Python :: 3.11
Classifier: Programming Language :: Python :: 3.12
Classifier: Programming Language :: Python :: 3.8
Provides-Extra: all
Requires-Dist: nautobot (>=2.0.0,<3.0.0)
Requires-Dist: py-populate-dcim-lib (>=0.1.2,<0.2.0)
Project-URL: Documentation, https://docs.nautobot.com/projects/py-populate-dcim/en/latest/
Project-URL: Repository, https://git.autonaut.dev/autonaut/nautobot-app-py-populate-dcim
